emojientities/__init__.py
emojientities/__main__.py
emojientities/_version.py
emojientities/emojis.py
emojientities-0.1.6.dist-info/LICENSE
emojientities-0.1.6.dist-info/METADATA
emojientities-0.1.6.dist-info/WHEEL
emojientities-0.1.6.dist-info/top_level.txt
emojientities-0.1.6.dist-info/RECORD
