Metadata-Version: 2.1
Name: emojientities
Version: 0.1.6
Summary: provides `string.emojis` (all emoji chars from unicode.org)
Home-page: https://gitlab.com/christoph.fink/python-emojientities
Author: Christoph Fink
Author-email: christoph@christophfink.com
License: GPLv3
Platform: UNKNOWN
Classifier: Programming Language :: Python :: 3
Classifier: License :: OSI Approved :: GNU General Public License v3 (GPLv3)
Classifier: Operating System :: OS Independent
Requires-Dist: requests
